colablinter/__init__.py
colablinter/command.py
colablinter/logger.py
colablinter/magics.py
colablinter-0.1.4.dist-info/licenses/LICENSE
colablinter-0.1.4.dist-info/METADATA
colablinter-0.1.4.dist-info/WHEEL
colablinter-0.1.4.dist-info/top_level.txt
colablinter-0.1.4.dist-info/RECORD
