Metadata-Version: 2.4
Name: colablinter
Version: 0.1.4
Summary: Linting and formatting Python code in Google Colab.
Author-email: RektPunk <rektpunk@gmail.com>
Project-URL: repository, https://github.com/RektPunk/colablinter
Keywords: jupyter,colab,ipython,magic,ruff,isort,linter
Classifier: Programming Language :: Python :: 3
Classifier: License :: OSI Approved :: MIT License
Classifier: Operating System :: OS Independent
Classifier: Framework :: IPython
Requires-Python: >=3.12
License-File: LICENSE
Requires-Dist: ipython>=7.34.0
Requires-Dist: ruff>=0.14.7
Dynamic: license-file
